bin/__init__.py
bin/calculateEngravingDefaults.py
bin/checkAnchors.py
bin/cleanFont.py
bin/generateMetadata.py
bin/importAnchors.py
bin/importID.py
smufolib/__init__.py
smufolib/_version.py
smufolib/cli.py
smufolib/config.py
smufolib/request.py
smufolib/metadata/bravura_metadata.json
smufolib/metadata/classes.json
smufolib/metadata/glyphnames.json
smufolib/metadata/ranges.json
smufolib/objects/__init__.py
smufolib/objects/_lib.py
smufolib/objects/engravingDefaults.py
smufolib/objects/font.py
smufolib/objects/glyph.py
smufolib/objects/layer.py
smufolib/objects/range.py
smufolib/objects/smufl.py
smufolib/utils/__init__.py
smufolib/utils/_annotations.py
smufolib/utils/converters.py
smufolib/utils/error.py
smufolib/utils/normalizers.py
smufolib/utils/rulers.py
smufolib/utils/scriptUtils.py
smufolib/utils/stdUtils.py
smufolib-0.7.2.dist-info/licenses/LICENSE
smufolib-0.7.2.dist-info/METADATA
smufolib-0.7.2.dist-info/WHEEL
smufolib-0.7.2.dist-info/entry_points.txt
smufolib-0.7.2.dist-info/top_level.txt
smufolib-0.7.2.dist-info/RECORD
