Metadata-Version: 2.4
Name: smufolib
Version: 0.7.2
Summary: FontParts-based library for SMuFL font scripting
Author-email: Knut Nergaard <knut.nergaard@gmail.com>
License: 
Project-URL: Homepage, https://github.com/knutnergaard/SMufoLib
Keywords: music notation,font design,SMuFL,UFO,FontParts
Classifier: Development Status :: 4 - Beta
Classifier: License :: OSI Approved :: MIT License
Classifier: Programming Language :: Python :: 3
Classifier: Programming Language :: Python :: 3.10
Classifier: Programming Language :: Python :: 3.11
Classifier: Programming Language :: Python :: 3.12
Classifier: Programming Language :: Python :: 3.13
Classifier: Programming Language :: Python :: 3 :: Only
Classifier: Operating System :: OS Independent
Requires-Python: >=3.10
License-File: LICENSE
Requires-Dist: fontParts
Requires-Dist: tqdm
Dynamic: license-file
